pylateral/__init__.py
pylateral/cache.py
pylateral/exceptions.py
pylateral/task_group_module.py
pylateral/task_module.py
pylateral/task_pool_module.py
pylateral/timeout.py
pylateral/util.py
tests/__init__.py
tests/test_cache.py
tests/test_task.py
tests/test_task_group.py
tests/test_task_pool.py
pylateral-1.0.0.dist-info/LICENSE
pylateral-1.0.0.dist-info/METADATA
pylateral-1.0.0.dist-info/WHEEL
pylateral-1.0.0.dist-info/top_level.txt
pylateral-1.0.0.dist-info/RECORD
