Metadata-Version: 2.1
Name: pylateral
Version: 1.0.0
Summary: Intuitive multi-threaded task processing in python.
Home-page: https://boxysean.github.io/pylateral/
Author: Sean McIntyre
Author-email: boxysean@gmail.com
License: MIT
Platform: UNKNOWN
